ipfx/__init__.py
ipfx/_schemas.py
ipfx/chirp.py
ipfx/data_access.py
ipfx/data_set_features.py
ipfx/data_set_utils.py
ipfx/ephys_data_set.py
ipfx/epochs.py
ipfx/error.py
ipfx/feature_extractor.py
ipfx/feature_record.py
ipfx/feature_vectors.py
ipfx/lab_notebook_reader.py
ipfx/lims_queries.py
ipfx/logging_utils.py
ipfx/nwb_append.py
ipfx/plot_qc_figures.py
ipfx/qc_feature_evaluator.py
ipfx/qc_feature_extractor.py
ipfx/qc_features.py
ipfx/script_utils.py
ipfx/spike_detector.py
ipfx/spike_features.py
ipfx/spike_train_features.py
ipfx/stim_features.py
ipfx/stimulus.py
ipfx/stimulus_protocol_analysis.py
ipfx/string_utils.py
ipfx/subthresh_features.py
ipfx/sweep.py
ipfx/sweep_props.py
ipfx/time_series_utils.py
ipfx/utilities.py
ipfx/version.txt
ipfx/attach_metadata/README.md
ipfx/attach_metadata/__init__.py
ipfx/attach_metadata/__main__.py
ipfx/attach_metadata/_schemas.py
ipfx/attach_metadata/doc/design.md
ipfx/attach_metadata/sink/__init__.py
ipfx/attach_metadata/sink/dandi_yaml_sink.py
ipfx/attach_metadata/sink/metadata_sink.py
ipfx/attach_metadata/sink/nwb2_sink.py
ipfx/bin/README.md
ipfx/bin/__init__.py
ipfx/bin/generate_fx_input.py
ipfx/bin/generate_pipeline_input.py
ipfx/bin/generate_qc_input.py
ipfx/bin/generate_se_input.py
ipfx/bin/get_fx_output.py
ipfx/bin/make_stimulus_ontology.py
ipfx/bin/mcc-output.json
ipfx/bin/mcc_get_settings.py
ipfx/bin/misc-settings.json
ipfx/bin/nwb_to_pdf.py
ipfx/bin/pipeline_from_specimen_id.py
ipfx/bin/plot_ephys_nwb.py
ipfx/bin/run_chirp_fv_extraction.py
ipfx/bin/run_feature_collection.py
ipfx/bin/run_feature_extraction.py
ipfx/bin/run_feature_vector_extraction.py
ipfx/bin/run_pipeline.py
ipfx/bin/run_pipeline_from_nwb_file.py
ipfx/bin/run_qc.py
ipfx/bin/run_sweep_extraction.py
ipfx/bin/run_synphys_feature_vector_extraction.py
ipfx/bin/run_x_to_nwb_conversion.py
ipfx/bin/validate_experiment.py
ipfx/data_release/2020-06-26_human_file_manifest.csv
ipfx/data_release/2020-06-26_mouse_file_manifest.csv
IPFX-2.0.0.dist-info/AUTHORS.rst
IPFX-2.0.0.dist-info/LICENSE
IPFX-2.0.0.dist-info/METADATA
IPFX-2.0.0.dist-info/WHEEL
IPFX-2.0.0.dist-info/top_level.txt
IPFX-2.0.0.dist-info/RECORD
