Metadata-Version: 2.1
Name: IPFX
Version: 2.0.0
Summary: Intrinsic Physiology Feature Extractor (IPFX) - tool for computing neuronal features from the intracellular electrophysiological recordings
Home-page: https://github.com/AllenInstitute/ipfx
Author: Allen Institute for Brain Science
Author-email: Marmot@AllenInstitute.onmicrosoft.com
Keywords: neuroscience,bioinformatics,scientific
Classifier: Development Status :: 5 - Production/Stable
Classifier: Intended Audience :: Science/Research
Classifier: License :: Other/Proprietary License
Classifier: Natural Language :: English
Classifier: Operating System :: OS Independent
Classifier: Programming Language :: Python :: 3.9
Classifier: Programming Language :: Python :: 3.11
Classifier: Topic :: Scientific/Engineering :: Bio-Informatics
License-File: LICENSE
License-File: AUTHORS.rst
Requires-Dist: allensdk
Requires-Dist: argschema
Requires-Dist: dictdiffer
Requires-Dist: h5py
Requires-Dist: marshmallow
Requires-Dist: matplotlib
Requires-Dist: methodtools
Requires-Dist: numpy
Requires-Dist: pandas
Requires-Dist: pg8000
Requires-Dist: pillow
Requires-Dist: pyabf
Requires-Dist: pynwb==2.2.0
Requires-Dist: pyYAML
Requires-Dist: ruamel.yaml<0.18.0
Requires-Dist: scipy
Requires-Dist: simplejson
Requires-Dist: watchdog
